{"song":{"player1":"bf-pixel-glitch2","notes":[{"sectionNotes":[[0,2,225],[300,0,150],[525,0,0],[600,1,225],[900,2,225]],"lengthInSteps":16,"mustHitSection":false},{"sectionNotes":[[1500,0,150],[1725,0,0],[1800,1,225],[1200,3,225],[2100,0,225]],"lengthInSteps":16,"mustHitSection":true},{"sectionNotes":[[2400,0,225],[2700,1,225],[3000,3,225],[3300,1,225]],"lengthInSteps":16,"mustHitSection":false},{"sectionNotes":[[3600,0,225],[3900,1,225],[4200,2,225],[4500,3,225]],"lengthInSteps":16,"mustHitSection":true},{"sectionNotes":[[5700,2,225],[4800,3,225],[5100,1,150],[5325,1,0],[5400,3,225]],"lengthInSteps":16,"mustHitSection":false},{"sectionNotes":[[6000,2,225],[6300,3,150],[6525,3,0],[6600,2,225],[6900,0,225]],"lengthInSteps":16,"mustHitSection":true},{"sectionNotes":[[7200,1,225],[7500,0,225],[7800,3,225],[8100,0,225]],"lengthInSteps":16,"mustHitSection":false},{"sectionNotes":[[8400,1,225],[8700,0,225],[9000,2,225],[9300,3,225]],"lengthInSteps":16,"mustHitSection":true},{"sectionNotes":[[9600,2,225],[9900,0,225],[10200,1,0],[10350,1,0],[10500,2,0],[10650,2,0]],"lengthInSteps":16,"mustHitSection":false},{"sectionNotes":[[10800,3,225],[11100,0,225],[11550,1,0],[11400,1,0],[11700,0,0],[11850,0,0]],"lengthInSteps":16,"mustHitSection":true},{"sectionNotes":[[12000,0,225],[12300,1,225],[12750,3,0],[12600,3,0],[12900,1,0],[13050,1,0]],"lengthInSteps":16,"mustHitSection":false},{"sectionNotes":[[13200,0,225],[13500,1,225],[13800,2,0],[13950,2,0],[14100,3,0],[14250,3,0]],"lengthInSteps":16,"mustHitSection":true},{"sectionNotes":[[14400,3,0],[14550,3,0],[14700,1,225],[15000,3,0],[15150,3,0],[15300,2,225]],"lengthInSteps":16,"mustHitSection":false},{"sectionNotes":[[16500,0,225],[15900,3,225],[16350,2,0],[16200,2,0],[15750,2,0],[15600,2,0]],"lengthInSteps":16,"mustHitSection":true},{"sectionNotes":[[16950,1,0],[16800,1,0],[17250,0,0],[17100,0,0],[17400,3,0],[17550,3,0],[17850,0,0],[17700,0,0]],"lengthInSteps":16,"mustHitSection":false},{"sectionNotes":[[18150,1,0],[18000,1,0],[18450,0,0],[18300,0,0],[18750,2,0],[18600,2,0],[19050,3,0],[18900,3,0]],"lengthInSteps":16,"mustHitSection":true},{"sectionNotes":[[19200,2,0],[19500,2,0],[19800,2,0],[20100,2,0]],"lengthInSteps":16,"mustHitSection":true},{"sectionNotes":[[20400,2,0],[20550,2,0],[20700,2,0],[20850,2,0],[21000,2,0],[21150,2,0],[21300,2,0],[21450,2,0]],"lengthInSteps":16,"mustHitSection":true},{"sectionNotes":[[21600,2,225],[21900,0,150],[22125,0,0],[22200,1,225],[22500,2,225]],"lengthInSteps":16,"mustHitSection":false},{"sectionNotes":[[23100,0,150],[23325,0,0],[23400,1,225],[22800,3,225],[23700,0,225]],"lengthInSteps":16,"mustHitSection":true},{"sectionNotes":[[24000,0,225],[24300,1,225],[24600,3,225],[24900,1,225]],"lengthInSteps":16,"mustHitSection":false},{"sectionNotes":[[25200,0,225],[25500,1,225],[25800,2,225],[26100,3,225]],"lengthInSteps":16,"mustHitSection":true},{"sectionNotes":[[27300,2,225],[26400,3,225],[26700,1,150],[26925,1,0],[27000,3,225]],"lengthInSteps":16,"mustHitSection":false},{"sectionNotes":[[27600,2,225],[27900,3,150],[28125,3,0],[28200,2,225],[28500,0,225]],"lengthInSteps":16,"mustHitSection":true},{"sectionNotes":[[28800,1,225],[29100,0,225],[29400,3,225],[29700,0,225]],"lengthInSteps":16,"mustHitSection":false},{"sectionNotes":[[30000,1,225],[30300,0,225],[30600,2,225],[30900,3,225]],"lengthInSteps":16,"mustHitSection":true},{"sectionNotes":[[31800,1,0],[31950,1,0],[32100,2,0],[32250,2,0],[31350,2,0],[31200,2,0],[31650,0,0],[31500,0,0],[31875,1,0],[32025,1,0]],"lengthInSteps":16,"mustHitSection":false},{"sectionNotes":[[33150,1,0],[33000,1,0],[33300,0,0],[33450,0,0],[32550,3,0],[32400,3,0],[32850,0,0],[32700,0,0],[33075,1,0],[33225,1,0]],"lengthInSteps":16,"mustHitSection":true},{"sectionNotes":[[34350,3,0],[34200,3,0],[34500,1,0],[34650,1,0],[33750,0,0],[33825,0,0],[33600,0,0],[34050,1,0],[34125,1,0],[33900,1,0],[34425,3,0],[34575,1,0],[34725,1,0]],"lengthInSteps":16,"mustHitSection":false},{"sectionNotes":[[35400,2,0],[35550,2,0],[35700,3,0],[35850,3,0],[34950,0,0],[35025,0,0],[34800,0,0],[35250,1,0],[35325,1,0],[35100,1,0],[35625,2,0],[35925,3,0],[35775,3,0]],"lengthInSteps":16,"mustHitSection":true},{"sectionNotes":[[36000,3,0],[36150,3,0],[36600,3,0],[36750,3,0],[36525,1,0],[36300,1,150],[37050,2,0],[37125,2,0],[36900,2,0]],"lengthInSteps":16,"mustHitSection":false},{"sectionNotes":[[37950,2,0],[37800,2,0],[37350,2,0],[37200,2,0],[37725,3,0],[37500,3,150],[38250,0,0],[38325,0,0],[38100,0,0]],"lengthInSteps":16,"mustHitSection":true},{"lengthInSteps":16,"altAnim":false,"typeOfSection":0,"sectionNotes":[[38550,1,0],[38400,1,0],[38850,0,0],[38700,0,0],[39000,3,0],[39150,3,0],[39450,0,0],[39300,0,0],[38475,1,0],[38625,1,0],[38775,0,0],[38925,0,0],[39075,3,0],[39225,3,0],[39375,0,0],[39525,0,0]],"bpm":100,"startTime":0,"changeBPM":false,"endTime":0,"mustHitSection":false},{"lengthInSteps":16,"altAnim":false,"typeOfSection":0,"sectionNotes":[[39750,1,0],[39600,1,0],[40050,0,0],[39900,0,0],[40350,2,0],[40200,2,0],[40650,3,0],[40500,3,0],[39975,0,0],[39675,1,0],[40125,0,0],[39825,1,0],[40275,2,0],[40425,2,0],[40575,3,0],[40725,3,0]],"bpm":200,"startTime":0,"changeBPM":false,"endTime":0,"mustHitSection":true},{"lengthInSteps":16,"altAnim":false,"typeOfSection":0,"sectionNotes":[[40800,6,525],[40800,2,225],[41100,1,225],[41400,0,225],[41700,3,225]],"bpm":200,"startTime":0,"changeBPM":false,"endTime":0,"mustHitSection":false},{"lengthInSteps":16,"altAnim":false,"typeOfSection":0,"sectionNotes":[[42300,0,225],[42000,2,225],[42600,1,225],[42900,3,225]],"bpm":200,"startTime":0,"changeBPM":false,"endTime":0,"mustHitSection":false},{"lengthInSteps":16,"altAnim":false,"typeOfSection":0,"sectionNotes":[[43200,0,225],[43500,1,225],[43800,0,225],[44100,3,225]],"bpm":200,"startTime":0,"changeBPM":false,"endTime":0,"mustHitSection":false},{"lengthInSteps":16,"altAnim":false,"typeOfSection":0,"sectionNotes":[[44400,2,525],[45000,3,525]],"bpm":200,"startTime":0,"changeBPM":false,"endTime":0,"mustHitSection":false},{"lengthInSteps":16,"altAnim":false,"typeOfSection":0,"sectionNotes":[[45600,1,225],[46200,1,225],[45900,0,225],[46500,3,225]],"bpm":200,"startTime":0,"changeBPM":false,"endTime":0,"mustHitSection":false},{"lengthInSteps":16,"altAnim":false,"typeOfSection":0,"sectionNotes":[[46800,0,225],[47100,1,225],[47400,0,225],[47700,2,225]],"bpm":200,"startTime":0,"changeBPM":false,"endTime":0,"mustHitSection":false},{"lengthInSteps":16,"altAnim":false,"typeOfSection":0,"sectionNotes":[[48000,2,0],[48150,1,0],[48300,3,0],[48750,3,0],[48450,2,0],[48600,1,0],[48900,2,0],[49050,1,0]],"bpm":200,"startTime":0,"changeBPM":false,"endTime":0,"mustHitSection":false},{"lengthInSteps":16,"altAnim":false,"typeOfSection":0,"sectionNotes":[[49500,3,0],[49200,2,0],[49350,1,0],[49650,2,0],[49800,3,0],[49950,1,0],[50100,3,225]],"bpm":200,"startTime":0,"changeBPM":false,"endTime":0,"mustHitSection":false},{"lengthInSteps":16,"altAnim":false,"typeOfSection":0,"sectionNotes":[[50400,3,225],[50700,0,225],[51000,1,225],[51300,0,225]],"bpm":200,"startTime":0,"changeBPM":false,"endTime":0,"mustHitSection":true},{"lengthInSteps":16,"altAnim":false,"typeOfSection":0,"sectionNotes":[[51900,0,225],[52200,1,225],[51600,1,225],[52500,2,225]],"bpm":200,"startTime":0,"changeBPM":false,"endTime":0,"mustHitSection":true},{"lengthInSteps":16,"altAnim":false,"typeOfSection":0,"sectionNotes":[[53100,1,225],[52800,3,225],[53400,3,225],[53700,2,300]],"bpm":200,"startTime":0,"changeBPM":false,"endTime":0,"mustHitSection":true},{"lengthInSteps":16,"altAnim":false,"typeOfSection":0,"sectionNotes":[[54000,2,525],[54600,0,525]],"bpm":200,"startTime":0,"changeBPM":false,"endTime":0,"mustHitSection":true},{"lengthInSteps":16,"altAnim":false,"typeOfSection":0,"sectionNotes":[[55200,1,225],[55800,1,225],[55500,0,225],[56100,2,225]],"bpm":200,"startTime":0,"changeBPM":false,"endTime":0,"mustHitSection":true},{"lengthInSteps":16,"altAnim":false,"typeOfSection":0,"sectionNotes":[[56700,1,225],[57300,2,225],[56400,3,225],[57000,3,225]],"bpm":200,"startTime":0,"changeBPM":false,"endTime":0,"mustHitSection":true},{"lengthInSteps":16,"altAnim":false,"typeOfSection":0,"sectionNotes":[[57600,1,0],[57750,0,0],[57900,2,0],[58050,1,0],[58200,0,0],[58350,2,0],[58500,1,0],[58650,0,0]],"bpm":200,"startTime":0,"changeBPM":false,"endTime":0,"mustHitSection":true},{"lengthInSteps":16,"altAnim":false,"typeOfSection":0,"sectionNotes":[[59400,3,0],[58800,1,0],[58950,0,0],[59100,2,0],[59250,1,0],[59550,2,0],[59700,0,225]],"bpm":200,"startTime":0,"changeBPM":false,"endTime":0,"mustHitSection":true},{"lengthInSteps":16,"altAnim":false,"typeOfSection":0,"sectionNotes":[[60000,2,225],[60300,0,150],[60525,0,0],[60600,1,225],[60900,2,225]],"bpm":200,"startTime":0,"changeBPM":false,"endTime":0,"mustHitSection":false},{"lengthInSteps":16,"altAnim":false,"typeOfSection":0,"sectionNotes":[[61500,0,150],[61725,0,0],[61800,1,225],[61200,3,225],[62100,0,225]],"bpm":200,"startTime":0,"changeBPM":false,"endTime":0,"mustHitSection":true},{"lengthInSteps":16,"altAnim":false,"typeOfSection":0,"sectionNotes":[[62400,0,225],[62700,1,225],[63000,3,225],[63300,1,225]],"bpm":200,"startTime":0,"changeBPM":false,"endTime":0,"mustHitSection":false},{"lengthInSteps":16,"altAnim":false,"typeOfSection":0,"sectionNotes":[[63600,0,225],[63900,1,225],[64200,2,225],[64500,3,225]],"bpm":200,"startTime":0,"changeBPM":false,"endTime":0,"mustHitSection":true},{"lengthInSteps":16,"altAnim":false,"typeOfSection":0,"sectionNotes":[[65700,2,225],[64800,3,225],[65100,1,150],[65325,1,0],[65400,3,225]],"bpm":200,"startTime":0,"changeBPM":false,"endTime":0,"mustHitSection":false},{"lengthInSteps":16,"altAnim":false,"typeOfSection":0,"sectionNotes":[[66000,2,225],[66300,3,150],[66525,3,0],[66600,2,225],[66900,0,225]],"bpm":200,"startTime":0,"changeBPM":false,"endTime":0,"mustHitSection":true},{"lengthInSteps":16,"altAnim":false,"typeOfSection":0,"sectionNotes":[[67200,1,225],[67500,0,225],[67800,3,225],[68100,0,225]],"bpm":200,"startTime":0,"changeBPM":false,"endTime":0,"mustHitSection":false},{"lengthInSteps":16,"altAnim":false,"typeOfSection":0,"sectionNotes":[[68400,1,225],[68700,0,225],[69000,2,225],[69300,3,225]],"bpm":200,"startTime":0,"changeBPM":false,"endTime":0,"mustHitSection":true},{"lengthInSteps":16,"altAnim":false,"typeOfSection":0,"sectionNotes":[[70200,1,0],[70350,1,0],[70500,2,0],[70650,2,0],[69750,2,0],[69600,2,0],[70050,0,0],[69900,0,0],[70275,1,0],[70425,1,0]],"bpm":200,"startTime":0,"changeBPM":false,"endTime":0,"mustHitSection":false},{"lengthInSteps":16,"altAnim":false,"typeOfSection":0,"sectionNotes":[[71550,1,0],[71400,1,0],[71700,0,0],[71850,0,0],[70950,3,0],[70800,3,0],[71250,0,0],[71100,0,0],[71475,1,0],[71625,1,0]],"bpm":200,"startTime":0,"changeBPM":false,"endTime":0,"mustHitSection":true},{"lengthInSteps":16,"altAnim":false,"typeOfSection":0,"sectionNotes":[[72750,3,0],[72600,3,0],[72900,1,0],[73050,1,0],[72150,0,0],[72225,0,0],[72000,0,0],[72450,1,0],[72525,1,0],[72300,1,0],[72825,3,0],[72975,1,0],[73125,1,0]],"bpm":200,"startTime":0,"changeBPM":false,"endTime":0,"mustHitSection":false},{"lengthInSteps":16,"altAnim":false,"typeOfSection":0,"sectionNotes":[[73800,2,0],[73950,2,0],[74100,3,0],[74250,3,0],[73350,0,0],[73425,0,0],[73200,0,0],[73650,1,0],[73725,1,0],[73500,1,0],[74025,2,0],[74325,3,0],[74175,3,0]],"bpm":200,"startTime":0,"changeBPM":false,"endTime":0,"mustHitSection":true},{"lengthInSteps":16,"altAnim":false,"typeOfSection":0,"sectionNotes":[[74400,3,0],[74550,3,0],[75000,3,0],[75150,3,0],[74925,1,0],[74700,1,150],[75450,2,0],[75525,2,0],[75300,2,0]],"bpm":200,"startTime":0,"changeBPM":false,"endTime":0,"mustHitSection":false},{"lengthInSteps":16,"altAnim":false,"typeOfSection":0,"sectionNotes":[[76350,2,0],[76200,2,0],[75750,2,0],[75600,2,0],[76125,3,0],[75900,3,150],[76650,0,0],[76725,0,0],[76500,0,0]],"bpm":200,"startTime":0,"changeBPM":false,"endTime":0,"mustHitSection":true},{"lengthInSteps":16,"altAnim":false,"typeOfSection":0,"sectionNotes":[[76950,1,0],[76800,1,0],[77250,0,0],[77100,0,0],[77400,3,0],[77550,3,0],[77850,0,0],[77700,0,0],[76875,1,0],[77025,1,0],[77175,0,0],[77325,0,0],[77475,3,0],[77625,3,0],[77775,0,0],[77925,0,0]],"bpm":200,"startTime":0,"changeBPM":false,"endTime":0,"mustHitSection":false},{"lengthInSteps":16,"altAnim":false,"typeOfSection":0,"sectionNotes":[[78150,1,0],[78000,1,0],[78450,0,0],[78300,0,0],[78750,2,0],[78600,2,0],[79050,3,0],[78900,3,0],[78375,0,0],[78075,1,0],[78525,0,0],[78225,1,0],[78675,2,0],[78825,2,0],[78975,3,0],[79125,3,0]],"bpm":200,"startTime":0,"changeBPM":false,"endTime":0,"mustHitSection":true},{"lengthInSteps":16,"altAnim":false,"typeOfSection":0,"sectionNotes":[[79200,2,900]],"bpm":200,"startTime":0,"changeBPM":false,"endTime":0,"mustHitSection":true},{"lengthInSteps":16,"altAnim":false,"typeOfSection":0,"sectionNotes":[],"bpm":200,"startTime":0,"changeBPM":false,"endTime":0,"mustHitSection":true},{"lengthInSteps":16,"altAnim":false,"typeOfSection":0,"sectionNotes":[],"bpm":200,"startTime":0,"changeBPM":false,"endTime":0,"mustHitSection":false},{"lengthInSteps":16,"altAnim":false,"typeOfSection":0,"sectionNotes":[],"bpm":200,"startTime":0,"changeBPM":false,"endTime":0,"mustHitSection":false}],"player2":"senpai-angry-glitch2","song":"Tearing","validScore":true,"needsVoices":false,"speed":2.8,"bpm":200}}